setup.py
kotlin/__init__.py
kotlin.egg-info/PKG-INFO
kotlin.egg-info/SOURCES.txt
kotlin.egg-info/dependency_links.txt
kotlin.egg-info/top_level.txt